hdfmap/__init__.py
hdfmap/eval_functions.py
hdfmap/file_functions.py
hdfmap/hdf_loader.py
hdfmap/hdfmap_class.py
hdfmap/logging.py
hdfmap/nexus.py
hdfmap/reloader_class.py
hdfmap-1.0.2.dist-info/licenses/LICENSE
hdfmap-1.0.2.dist-info/METADATA
hdfmap-1.0.2.dist-info/WHEEL
hdfmap-1.0.2.dist-info/top_level.txt
hdfmap-1.0.2.dist-info/RECORD
