Metadata-Version: 2.4
Name: hdfmap
Version: 1.0.2
Summary: Map objects within a HDF5 file and create a dataset namespace
Author-email: Dan Porter <dan.porter@diamond.ac.uk>
Maintainer-email: Dan Porter <dan.porter@diamond.ac.uk>
License:                                  Apache License
Project-URL: Homepage, https://github.com/DiamondLightSource/hdfmap
Project-URL: Documentation, https://diamondlightsource.github.io/hdfmap/
Project-URL: Repository, https://github.com/DiamondLightSource/hdfmap
Project-URL: Bug Tracker, https://github.com/DiamondLightSource/hdfmap
Project-URL: Changelog, https://github.com/DiamondLightSource/hdfmap/blob/master/README.md
Keywords: nexus
Classifier: Programming Language :: Python :: 3.10
Classifier: Intended Audience :: Science/Research
Classifier: Topic :: Scientific/Engineering :: Physics
Classifier: License :: OSI Approved :: Apache Software License
Classifier: Development Status :: 3 - Alpha
Requires-Python: >=3.10
License-File: LICENSE
Requires-Dist: numpy
Requires-Dist: h5py
Requires-Dist: hdf5plugin
Requires-Dist: asteval
Dynamic: license-file
